README.md
setup.py
musicxml_parser/__init__.py
musicxml_parser/scoreToPianoroll.py
musicxml_parser/smooth_dynamic.py
musicxml_parser/totalLengthHandler.py
musicxml_parser.egg-info/PKG-INFO
musicxml_parser.egg-info/SOURCES.txt
musicxml_parser.egg-info/dependency_links.txt
musicxml_parser.egg-info/not-zip-safe
musicxml_parser.egg-info/top_level.txt