Metadata-Version: 1.0
Name: musicxml-parser
Version: 0.1
Summary: A musicXML parser written in Python based on a SAX analyzer
Home-page: https://github.com/qsdfo/musicxml_parser
Author: Léopold Crestel
Author-email: crestel.leopold@gmail.com
License: MIT
Platform: UNKNOWN
